MANIFEST.in
setup.py
datacats/__init__.py
datacats/docker.py
datacats/environment.py
datacats/error.py
datacats/migrate.py
datacats/network.py
datacats/password.py
datacats/scripts.py
datacats/task.py
datacats/template.py
datacats/userprofile.py
datacats/validate.py
datacats/version.py
datacats.egg-info/PKG-INFO
datacats.egg-info/SOURCES.txt
datacats.egg-info/dependency_links.txt
datacats.egg-info/entry_points.txt
datacats.egg-info/not-zip-safe
datacats.egg-info/requires.txt
datacats.egg-info/top_level.txt
datacats/cli/__init__.py
datacats/cli/create.py
datacats/cli/deploy.py
datacats/cli/install.py
datacats/cli/less.py
datacats/cli/lesscd.py
datacats/cli/main.py
datacats/cli/manage.py
datacats/cli/migrate.py
datacats/cli/pull.py
datacats/cli/purge.py
datacats/cli/shell.py
datacats/cli/util.py
datacats/images/chart.png
datacats/images/datacats-footer.png
datacats/scripts/adjust_devini.py
datacats/scripts/check_connectivity.sh
datacats/scripts/clean_virtualenv.sh
datacats/scripts/compile_less.sh
datacats/scripts/datapusher.sh
datacats/scripts/install_ckan_plugin.sh
datacats/scripts/install_extra_packages.sh
datacats/scripts/install_package.sh
datacats/scripts/install_postgis.sh
datacats/scripts/install_reqs.sh
datacats/scripts/known_hosts
datacats/scripts/migrate.sh
datacats/scripts/paster.sh
datacats/scripts/paster_cd.sh
datacats/scripts/purge.sh
datacats/scripts/run_as_user.sh
datacats/scripts/shell.sh
datacats/scripts/ssh_config
datacats/scripts/update_add_admin.sh
datacats/scripts/web.sh
datacats/tests/__init__.py
datacats/tests/test_cli_parsing.py
datacats/tests/test_cli_pull.py
datacats/tests/test_style.py
datacats/tests/test_validate.py