Metadata-Version: 1.0
Name: datacats
Version: 1.1.0
Summary: CKAN Data Catalog Developer Tools built on Docker
Home-page: https://github.com/datacats/datacats
Author: Boxkite
Author-email: contact@boxkite.ca
License: AGPL3
Platform: UNKNOWN
